.bumpversion.cfg
.editorconfig
.gitattributes
.gitignore
.landscape.yml
.travis.yml
ABOUT.ETC.md
ABOUT.md
CODE_OF_CONDUCT.md
LICENSE.txt
MANIFEST.in
Makefile
README.md
appveyor.yml
setup.py
tox.ini
instakit/__init__.pxd
instakit/__init__.py
instakit/__version__.py
instakit/exporting.py
instakit.egg-info/PKG-INFO
instakit.egg-info/SOURCES.txt
instakit.egg-info/dependency_links.txt
instakit.egg-info/not-zip-safe
instakit.egg-info/requires.txt
instakit.egg-info/top_level.txt
instakit/abc/__init__.pxd
instakit/abc/__init__.py
instakit/comparators/__init__.pxd
instakit/comparators/__init__.py
instakit/comparators/ext/__init__.pxd
instakit/comparators/ext/__init__.py
instakit/comparators/ext/butteraugli.cc
instakit/comparators/ext/butteraugli.h
instakit/comparators/ext/butteraugli.pxd
instakit/comparators/ext/buttereye.cpp
instakit/comparators/ext/buttereye.pyx
instakit/data/acv/Vintage.acv
instakit/data/acv/blood orange by julia trotti.acv
instakit/data/acv/carousel by julia trotti.acv
instakit/data/acv/country.acv
instakit/data/acv/desert.acv
instakit/data/acv/dramaticsee.acv
instakit/data/acv/electric by julia trotti.acv
instakit/data/acv/exoticmountain.acv
instakit/data/acv/exoticmountain_light.acv
instakit/data/acv/fogy_blue.acv
instakit/data/acv/fresh_blue.acv
instakit/data/acv/green.acv
instakit/data/acv/humming bees by julia trotti.acv
instakit/data/acv/midnight hour by julia trotti.acv
instakit/data/acv/new_2_fresh_blue.acv
instakit/data/acv/red.acv
instakit/data/acv/sparks by julia trotti.acv
instakit/data/acv/trains.acv
instakit/data/acv/wild at heart by julia trotti.acv
instakit/data/acv/yellow.acv
instakit/data/hither/astronaut.png
instakit/data/hither/rocket.jpg
instakit/data/hither/scene.png
instakit/data/hither/scenebayer0.png
instakit/data/hither/scenenodither.png
instakit/data/icc/sRGB-IEC61966-2.1.icc
instakit/data/img/06-DSCN4771.JPG
instakit/data/img/430023_3625646599363_1219964362_3676052_834528487_n.jpg
instakit/data/img/472512_10100627861801935_22413710_51140672_988173580_o.jpg
instakit/data/img/indy-moving-into-my-move-in.jpg
instakit/data/img/max-hardcore-feline-strategy-advisor.jpg
instakit/data/lut/amatorka.png
