Metadata-Version: 2.1
Name: instakit
Version: 0.8.8
Summary: Image processors for django-imagekit - based on Pillow, SciPy, and scikit-image
Home-page: https://github.com/fish2000/instakit
Author: Alexander Böhn
Author-email: fish2000@gmail.com
License: MIT
Download-URL: https://github.com/fish2000/instakit/zipball/master
Keywords: django imagekit instakit fish2000 image processing image analysis image comparison halftone dithering Photoshop acv curves PIL Pillow Cython NumPy SciPy scikit-image
Platform: any
Classifier: Development Status :: 5 - Production/Stable
Classifier: License :: OSI Approved :: MIT License
Classifier: Intended Audience :: Developers
Classifier: Operating System :: MacOS
Classifier: Operating System :: Microsoft :: Windows
Classifier: Operating System :: OS Independent
Classifier: Operating System :: POSIX
Classifier: Operating System :: Unix
Classifier: Programming Language :: Python
Classifier: Programming Language :: Python :: 3
Classifier: Programming Language :: Python :: 3.5
Classifier: Programming Language :: Python :: 3.6
Classifier: Programming Language :: Python :: 3.7
